python_xena-0.6.0.dist-info/DESCRIPTION.rst
python_xena-0.6.0.dist-info/METADATA
python_xena-0.6.0.dist-info/RECORD
python_xena-0.6.0.dist-info/WHEEL
python_xena-0.6.0.dist-info/metadata.json
python_xena-0.6.0.dist-info/top_level.txt
xena/__init__.py
xena/exceptions.py
xena/helpers.py
xena/rest.py
xena/rest_sync.py
xena/serialization.py
xena/websocket.py
xena/proto/__init__.py
xena/proto/auth_pb2.py
xena/proto/balance_pb2.py
xena/proto/common_pb2.py
xena/proto/constants.py
xena/proto/constants_pb2.py
xena/proto/margin_pb2.py
xena/proto/market_pb2.py
xena/proto/order_pb2.py
xena/proto/positions_pb2.py
