Metadata-Version: 2.0
Name: python-xena
Version: 0.6.0
Summary: XenaExchange API python implementation
Home-page: UNKNOWN
Author: UNKNOWN
Author-email: UNKNOWN
License: MIT
Keywords: xena exchange api bitcoin ethereum btc eth neo
Platform: UNKNOWN
Classifier: Intended Audience :: Developers
Classifier: License :: OSI Approved :: MIT License
Classifier: Operating System :: OS Independent
Classifier: Programming Language :: Python :: 3
Classifier: Programming Language :: Python :: 3.5
Classifier: Programming Language :: Python :: 3.6
Classifier: Programming Language :: Python :: 3.7
Classifier: Programming Language :: Python
Classifier: Topic :: Software Development :: Libraries :: Python Modules
Requires-Dist: requests
Requires-Dist: six
Requires-Dist: pyOpenSSL
Requires-Dist: service-identity
Requires-Dist: dateparser
Requires-Dist: urllib3
Requires-Dist: chardet
Requires-Dist: certifi
Requires-Dist: cryptography
Requires-Dist: aiohttp
Requires-Dist: ecdsa
Requires-Dist: protobuf
Requires-Dist: simplejson
